LICENSE
MANIFEST.in
NEWS
README.rst
setup.py
metamagic.json.egg-info/PKG-INFO
metamagic.json.egg-info/SOURCES.txt
metamagic.json.egg-info/dependency_links.txt
metamagic.json.egg-info/top_level.txt
metamagic/json/__init__.py
metamagic/json/encoder.py
metamagic/json/_encoder/_encoder.c
metamagic/json/_encoder/_encoder.h
metamagic/json/_encoder/_encoder_buffer.c
metamagic/json/_encoder/_encoder_buffer.h
metamagic/json/_encoder/_encoder_stringify.c
metamagic/json/_encoder/_encoder_stringify.h
metamagic/json/tests/__init__.py
metamagic/json/tests/benchmark_encoder.py
metamagic/json/tests/test_decoder.py
metamagic/json/tests/test_encoder.py