Metadata-Version: 1.1
Name: metamagic.json
Version: 0.9.4
Summary: Fast JSON encoder
Home-page: http://github.com/sprymix/metamagic.json
Author: Sprymix Inc.
Author-email: info@sprymix.com
License: BSD
Keywords: json
Platform: any
Classifier: Development Status :: 5 - Production/Stable
Classifier: Intended Audience :: Developers
Classifier: License :: OSI Approved :: BSD License
Classifier: Operating System :: OS Independent
Classifier: Programming Language :: C
Classifier: Programming Language :: Python :: 3
Classifier: Programming Language :: Python :: 3.3
Classifier: Programming Language :: Python :: 3.4
